polars_fin-0.2.0.dist-info/METADATA
polars_fin-0.2.0.dist-info/WHEEL
polars_fin/__init__.py
polars_fin/_internal.abi3.so
polars_fin/_internal.pyi
polars_fin/typing.py
polars_fin-0.2.0.dist-info/RECORD
